mpt/__init__.py
mpt/hash.py
mpt/mpt.py
mpt/nibble_path.py
mpt/node.py
tests/__init__.py
tests/test_vectors.py
tests/tests.py
eth_mpt-0.2.0.dist-info/LICENSE
eth_mpt-0.2.0.dist-info/METADATA
eth_mpt-0.2.0.dist-info/WHEEL
eth_mpt-0.2.0.dist-info/top_level.txt
eth_mpt-0.2.0.dist-info/RECORD
