Metadata-Version: 2.1
Name: eth_mpt
Version: 0.2.0
Summary: A simlpe Merkle Patricia Trie implementation
Home-page: https://github.com/popzxc/merkle-patricia-trie
Author: Igor Aleksanov
Author-email: popzxc@yandex.com
License: UNKNOWN
Platform: UNKNOWN
Classifier: Programming Language :: Python :: 3
Classifier: License :: OSI Approved :: MIT License
Classifier: Operating System :: OS Independent
Classifier: Topic :: Security :: Cryptography
